quos/__init__.py
quos/qblo.xlsm
quos/quos.html
quos/quos.xlsm
quos/icons/0.jpg
quos/icons/1.jpg
quos/icons/C.jpg
quos/icons/Cd.jpg
quos/icons/H.jpg
quos/icons/I.jpg
quos/icons/K.jpg
quos/icons/M.jpg
quos/icons/O.jpg
quos/icons/Ph.jpg
quos/icons/Pp.jpg
quos/icons/Q.jpg
quos/icons/Rx.jpg
quos/icons/Ry.jpg
quos/icons/Rz.jpg
quos/icons/S.jpg
quos/icons/Sw.jpg
quos/icons/T.jpg
quos/icons/U.jpg
quos/icons/V.jpg
quos/icons/X.jpg
quos/icons/Y.jpg
quos/icons/Z.jpg
quos/icons/__init__.py
quos/icons/iSw.jpg
quos/icons/w/x010.jpg
quos/icons/w/x011.jpg
quos/icons/w/x020.jpg
quos/icons/w/x030.jpg
quos/icons/w/x031.jpg
quos/icons/w/x040.jpg
quos/icons/w/x050.jpg
quos/icons/w/x060.jpg
quos/icons/w/x070.jpg
quos/icons/w/x080.jpg
quos/icons/w/x090.jpg
quos/icons/w/x100.jpg
quos/icons/w/x110.jpg
quos/icons/w/x120.jpg
quos/icons/w/x130.jpg
quos/icons/w/x131.jpg
quos/icons/w/x140.jpg
quos/icons/w/x141.jpg
quos/icons/w/x150.jpg
quos/icons/w/x160.jpg
quos/icons/w/x170.jpg
quos/icons/w/x180.jpg
quos/icons/w/x190.jpg
quos/icons/w/x200.jpg
quos/icons/w/x210.jpg
quos/icons/w/x260.jpg
quos/icons/w/x280.jpg
quos/icons/w/x290.jpg
quos/icons/w/x291.jpg
quos/icons/w/x420.jpg
quos/icons/w/x430.jpg
quos/icons/w/x440.jpg
quos-0.0.16.dist-info/LICENSE
quos-0.0.16.dist-info/METADATA
quos-0.0.16.dist-info/WHEEL
quos-0.0.16.dist-info/top_level.txt
quos-0.0.16.dist-info/RECORD
