Metadata-Version: 2.1
Name: quos
Version: 0.0.16
Summary: Quos package simplifies plotting and simulating a quantum computing circuit employing oscillatory qudits.
Home-page: https://github.com/lapyl/quos
Author: Lalit Patel
Author-email: LLSR@att.net
Classifier: Programming Language :: Python :: 3
Classifier: License :: OSI Approved :: MIT License
Classifier: Operating System :: OS Independent
Requires-Python: >=3.6
License-File: LICENSE
Requires-Dist: matplotlib
Requires-Dist: pandas
